austin/.__init__.py.un~
austin/.scipy.py.swp
austin/.scipy.py.un~
austin/__init__.py
austin/scipy.py
austin-2016.0.1.dist-info/METADATA
austin-2016.0.1.dist-info/WHEEL
austin-2016.0.1.dist-info/RECORD
