Metadata-Version: 1.2
Name: austin
Version: 2016.0.1
Summary: austin scipy package
Home-page: https://github.com/Carreau/austin
License: UNKNOWN
Author: Matthias Bussonnier
Author-email: bussonniermatthias@gmail.com
Classifier: License :: OSI Approved :: MIT License
